calamities/__init__.py
calamities/_version.py
calamities/app.py
calamities/color.py
calamities/config.py
calamities/context.py
calamities/cursor.py
calamities/file.py
calamities/font.py
calamities/keyboard.py
calamities/layout.py
calamities/prompt.py
calamities/text.py
calamities/view.py
calamities/input/__init__.py
calamities/input/choice.py
calamities/input/file.py
calamities/input/pattern.py
calamities/input/text.py
calamities/pattern/__init__.py
calamities/pattern/glob.py
calamities/pattern/re.py
calamities-0.0.16.dist-info/METADATA
calamities-0.0.16.dist-info/WHEEL
calamities-0.0.16.dist-info/top_level.txt
calamities-0.0.16.dist-info/RECORD
