Metadata-Version: 2.1
Name: calamities
Version: 0.0.16
Summary: Terminal user interface library
Home-page: https://github.com/HippocampusGirl/calamities
Author: Lea Waller
Author-email: lea.waller@charite.de
License: UNKNOWN
Keywords: curses interface terminal
Platform: any
Classifier: Development Status :: 3 - Alpha
Classifier: Intended Audience :: Developers
Classifier: Operating System :: OS Independent
Classifier: License :: OSI Approved :: GNU General Public License v3 or later (GPLv3+)
Classifier: Programming Language :: Python
Classifier: Programming Language :: Python :: 3.7
Classifier: Programming Language :: Python :: 3.8
Classifier: Topic :: Software Development :: Libraries :: Python Modules
Requires-Python: !=3.0.*,!=3.1.*,!=3.2.*,>=2.7
Requires-Dist: inflect (>=4.1.0)
Requires-Dist: numpy
